{
	"polozky": [
		{
			"okres": "Okres/3100",
			"absolventiSkolAMladistvi": 656,
			"dosazitelniUchazeci15_64": 30006,
			"mesic": "07",
			"noveHlasenaAUvolnenaVPM": 4533,
			"noveHlaseniUchazeci": 3321,
			"obsazenaAZrusenaVPM": 4365,
			"osobySeZdravotnimPostizenim": 2008,
			"pocetOsobPobirajicichPodporu": 7866,
			"pocetUchazecuNa1VPM": 0.3316086401,
			"podilNezamestnanychOsobPNO": 3.4340333927,
			"rok": "2021",
			"uchazeciOZamestnaniUoZ": 31917,
			"uchazeciOZamestnaniUoZZeny": 16681,
			"volnaPracovnaMistaVPM": 96249,
			"vyrazeniUchazeci": 3309,
			"celkemObyvatelstvo15_64": 873783
		},
		{
			"okres": "Okres/3201",
			"absolventiSkolAMladistvi": 45,
			"dosazitelniUchazeci15_64": 1215,
			"mesic": "07",
			"noveHlasenaAUvolnenaVPM": 313,
			"noveHlaseniUchazeci": 255,
			"obsazenaAZrusenaVPM": 307,
			"osobySeZdravotnimPostizenim": 180,
			"pocetOsobPobirajicichPodporu": 608,
			"pocetUchazecuNa1VPM": 0.5216392187,
			"podilNezamestnanychOsobPNO": 1.9564587292,
			"rok": "2021",
			"uchazeciOZamestnaniUoZ": 1362,
			"uchazeciOZamestnaniUoZZeny": 776,
			"volnaPracovnaMistaVPM": 2611,
			"vyrazeniUchazeci": 257,
			"celkemObyvatelstvo15_64": 62102
		},
		{
			"okres": "Okres/3202",
			"absolventiSkolAMladistvi": 84,
			"dosazitelniUchazeci15_64": 2100,
			"mesic": "07",
			"noveHlasenaAUvolnenaVPM": 382,
			"noveHlaseniUchazeci": 243,
			"obsazenaAZrusenaVPM": 468,
			"osobySeZdravotnimPostizenim": 287,
			"pocetOsobPobirajicichPodporu": 709,
			"pocetUchazecuNa1VPM": 0.5172648796,
			"podilNezamestnanychOsobPNO": 3.4230944774,
			"rok": "2021",
			"uchazeciOZamestnaniUoZ": 2277,
			"uchazeciOZamestnaniUoZZeny": 1205,
			"volnaPracovnaMistaVPM": 4402,
			"vyrazeniUchazeci": 241,
			"celkemObyvatelstvo15_64": 61348
		},
		{
			"okres": "Okres/3203",
			"absolventiSkolAMladistvi": 211,
			"dosazitelniUchazeci15_64": 5190,
			"mesic": "07",
			"noveHlasenaAUvolnenaVPM": 477,
			"noveHlaseniUchazeci": 494,
			"obsazenaAZrusenaVPM": 376,
			"osobySeZdravotnimPostizenim": 490,
			"pocetOsobPobirajicichPodporu": 1385,
			"pocetUchazecuNa1VPM": 1.3835920177,
			"podilNezamestnanychOsobPNO": 4.8840163742,
			"rok": "2021",
			"uchazeciOZamestnaniUoZ": 5616,
			"uchazeciOZamestnaniUoZZeny": 3055,
			"volnaPracovnaMistaVPM": 4059,
			"vyrazeniUchazeci": 467,
			"celkemObyvatelstvo15_64": 106265
		},
		{
			"okres": "Okres/3204",
			"absolventiSkolAMladistvi": 113,
			"dosazitelniUchazeci15_64": 2658,
			"mesic": "07",
			"noveHlasenaAUvolnenaVPM": 594,
			"noveHlaseniUchazeci": 371,
			"obsazenaAZrusenaVPM": 727,
			"osobySeZdravotnimPostizenim": 480,
			"pocetOsobPobirajicichPodporu": 1023,
			"pocetUchazecuNa1VPM": 0.7582851131,
			"podilNezamestnanychOsobPNO": 4.0549199085,
			"rok": "2021",
			"uchazeciOZamestnaniUoZ": 2883,
			"uchazeciOZamestnaniUoZZeny": 1667,
			"volnaPracovnaMistaVPM": 3802,
			"vyrazeniUchazeci": 390,
			"celkemObyvatelstvo15_64": 65550
		},
		{
			"okres": "Okres/3205",
			"absolventiSkolAMladistvi": 66,
			"dosazitelniUchazeci15_64": 1463,
			"mesic": "07",
			"noveHlasenaAUvolnenaVPM": 389,
			"noveHlaseniUchazeci": 252,
			"obsazenaAZrusenaVPM": 443,
			"osobySeZdravotnimPostizenim": 327,
			"pocetOsobPobirajicichPodporu": 566,
			"pocetUchazecuNa1VPM": 0.6529531568,
			"podilNezamestnanychOsobPNO": 3.0468375784,
			"rok": "2021",
			"uchazeciOZamestnaniUoZ": 1603,
			"uchazeciOZamestnaniUoZZeny": 950,
			"volnaPracovnaMistaVPM": 2455,
			"vyrazeniUchazeci": 227,
			"celkemObyvatelstvo15_64": 48017
		},
		{
			"okres": "Okres/3206",
			"absolventiSkolAMladistvi": 126,
			"dosazitelniUchazeci15_64": 3241,
			"mesic": "07",
			"noveHlasenaAUvolnenaVPM": 403,
			"noveHlaseniUchazeci": 408,
			"obsazenaAZrusenaVPM": 620,
			"osobySeZdravotnimPostizenim": 322,
			"pocetOsobPobirajicichPodporu": 967,
			"pocetUchazecuNa1VPM": 0.6481102216,
			"podilNezamestnanychOsobPNO": 4.603300855,
			"rok": "2021",
			"uchazeciOZamestnaniUoZ": 3481,
			"uchazeciOZamestnaniUoZZeny": 1950,
			"volnaPracovnaMistaVPM": 5371,
			"vyrazeniUchazeci": 411,
			"celkemObyvatelstvo15_64": 70406
		},
		{
			"okres": "Okres/3207",
			"absolventiSkolAMladistvi": 67,
			"dosazitelniUchazeci15_64": 1708,
			"mesic": "07",
			"noveHlasenaAUvolnenaVPM": 780,
			"noveHlaseniUchazeci": 279,
			"obsazenaAZrusenaVPM": 1052,
			"osobySeZdravotnimPostizenim": 234,
			"pocetOsobPobirajicichPodporu": 736,
			"pocetUchazecuNa1VPM": 0.1929067565,
			"podilNezamestnanychOsobPNO": 2.0054245089,
			"rok": "2021",
			"uchazeciOZamestnaniUoZ": 1833,
			"uchazeciOZamestnaniUoZZeny": 1071,
			"volnaPracovnaMistaVPM": 9502,
			"vyrazeniUchazeci": 242,
			"celkemObyvatelstvo15_64": 85169
		},
		{
			"okres": "Okres/3208",
			"absolventiSkolAMladistvi": 126,
			"dosazitelniUchazeci15_64": 2782,
			"mesic": "07",
			"noveHlasenaAUvolnenaVPM": 825,
			"noveHlaseniUchazeci": 380,
			"obsazenaAZrusenaVPM": 616,
			"osobySeZdravotnimPostizenim": 361,
			"pocetOsobPobirajicichPodporu": 933,
			"pocetUchazecuNa1VPM": 0.758114374,
			"podilNezamestnanychOsobPNO": 4.3007760566,
			"rok": "2021",
			"uchazeciOZamestnaniUoZ": 2943,
			"uchazeciOZamestnaniUoZZeny": 1591,
			"volnaPracovnaMistaVPM": 3882,
			"vyrazeniUchazeci": 346,
			"celkemObyvatelstvo15_64": 64686
		},
		{
			"okres": "Okres/3209",
			"absolventiSkolAMladistvi": 92,
			"dosazitelniUchazeci15_64": 2191,
			"mesic": "07",
			"noveHlasenaAUvolnenaVPM": 2996,
			"noveHlaseniUchazeci": 351,
			"obsazenaAZrusenaVPM": 2990,
			"osobySeZdravotnimPostizenim": 173,
			"pocetOsobPobirajicichPodporu": 887,
			"pocetUchazecuNa1VPM": 0.1243376331,
			"podilNezamestnanychOsobPNO": 1.8122864918,
			"rok": "2021",
			"uchazeciOZamestnaniUoZ": 2323,
			"uchazeciOZamestnaniUoZZeny": 1302,
			"volnaPracovnaMistaVPM": 18683,
			"vyrazeniUchazeci": 448,
			"celkemObyvatelstvo15_64": 120897
		},
		{
			"okres": "Okres/3210",
			"absolventiSkolAMladistvi": 70,
			"dosazitelniUchazeci15_64": 2326,
			"mesic": "07",
			"noveHlasenaAUvolnenaVPM": 1550,
			"noveHlaseniUchazeci": 284,
			"obsazenaAZrusenaVPM": 1127,
			"osobySeZdravotnimPostizenim": 181,
			"pocetOsobPobirajicichPodporu": 764,
			"pocetUchazecuNa1VPM": 0.5243151412,
			"podilNezamestnanychOsobPNO": 2.4048303385,
			"rok": "2021",
			"uchazeciOZamestnaniUoZ": 2469,
			"uchazeciOZamestnaniUoZZeny": 1392,
			"volnaPracovnaMistaVPM": 4709,
			"vyrazeniUchazeci": 370,
			"celkemObyvatelstvo15_64": 96722
		},
		{
			"okres": "Okres/3211",
			"absolventiSkolAMladistvi": 99,
			"dosazitelniUchazeci15_64": 2995,
			"mesic": "07",
			"noveHlasenaAUvolnenaVPM": 540,
			"noveHlaseniUchazeci": 372,
			"obsazenaAZrusenaVPM": 539,
			"osobySeZdravotnimPostizenim": 393,
			"pocetOsobPobirajicichPodporu": 955,
			"pocetUchazecuNa1VPM": 0.7139019476,
			"podilNezamestnanychOsobPNO": 4.120973623,
			"rok": "2021",
			"uchazeciOZamestnaniUoZ": 3189,
			"uchazeciOZamestnaniUoZZeny": 1645,
			"volnaPracovnaMistaVPM": 4467,
			"vyrazeniUchazeci": 397,
			"celkemObyvatelstvo15_64": 72677
		},
		{
			"okres": "Okres/3212",
			"absolventiSkolAMladistvi": 54,
			"dosazitelniUchazeci15_64": 1121,
			"mesic": "07",
			"noveHlasenaAUvolnenaVPM": 126,
			"noveHlaseniUchazeci": 166,
			"obsazenaAZrusenaVPM": 194,
			"osobySeZdravotnimPostizenim": 298,
			"pocetOsobPobirajicichPodporu": 464,
			"pocetUchazecuNa1VPM": 1.2333333333,
			"podilNezamestnanychOsobPNO": 3.2105624928,
			"rok": "2021",
			"uchazeciOZamestnaniUoZ": 1221,
			"uchazeciOZamestnaniUoZZeny": 711,
			"volnaPracovnaMistaVPM": 990,
			"vyrazeniUchazeci": 160,
			"celkemObyvatelstvo15_64": 34916
		},
		{
			"okres": "Okres/3301",
			"absolventiSkolAMladistvi": 166,
			"dosazitelniUchazeci15_64": 3591,
			"mesic": "07",
			"noveHlasenaAUvolnenaVPM": 552,
			"noveHlaseniUchazeci": 523,
			"obsazenaAZrusenaVPM": 498,
			"osobySeZdravotnimPostizenim": 562,
			"pocetOsobPobirajicichPodporu": 1248,
			"pocetUchazecuNa1VPM": 0.7243809524,
			"podilNezamestnanychOsobPNO": 2.8794342164,
			"rok": "2021",
			"uchazeciOZamestnaniUoZ": 3803,
			"uchazeciOZamestnaniUoZZeny": 2047,
			"volnaPracovnaMistaVPM": 5250,
			"vyrazeniUchazeci": 489,
			"celkemObyvatelstvo15_64": 124712
		},
		{
			"okres": "Okres/3302",
			"absolventiSkolAMladistvi": 67,
			"dosazitelniUchazeci15_64": 1605,
			"mesic": "07",
			"noveHlasenaAUvolnenaVPM": 337,
			"noveHlaseniUchazeci": 196,
			"obsazenaAZrusenaVPM": 492,
			"osobySeZdravotnimPostizenim": 271,
			"pocetOsobPobirajicichPodporu": 402,
			"pocetUchazecuNa1VPM": 0.3953917051,
			"podilNezamestnanychOsobPNO": 4.0588726197,
			"rok": "2021",
			"uchazeciOZamestnaniUoZ": 1716,
			"uchazeciOZamestnaniUoZZeny": 924,
			"volnaPracovnaMistaVPM": 4340,
			"vyrazeniUchazeci": 250,
			"celkemObyvatelstvo15_64": 39543
		},
		{
			"okres": "Okres/3303",
			"absolventiSkolAMladistvi": 46,
			"dosazitelniUchazeci15_64": 1008,
			"mesic": "07",
			"noveHlasenaAUvolnenaVPM": 275,
			"noveHlaseniUchazeci": 197,
			"obsazenaAZrusenaVPM": 181,
			"osobySeZdravotnimPostizenim": 225,
			"pocetOsobPobirajicichPodporu": 446,
			"pocetUchazecuNa1VPM": 0.6336134454,
			"podilNezamestnanychOsobPNO": 1.7884072885,
			"rok": "2021",
			"uchazeciOZamestnaniUoZ": 1131,
			"uchazeciOZamestnaniUoZZeny": 670,
			"volnaPracovnaMistaVPM": 1785,
			"vyrazeniUchazeci": 273,
			"celkemObyvatelstvo15_64": 56363
		},
		{
			"okres": "Okres/3305",
			"absolventiSkolAMladistvi": 66,
			"dosazitelniUchazeci15_64": 1051,
			"mesic": "07",
			"noveHlasenaAUvolnenaVPM": 455,
			"noveHlaseniUchazeci": 199,
			"obsazenaAZrusenaVPM": 547,
			"osobySeZdravotnimPostizenim": 188,
			"pocetOsobPobirajicichPodporu": 462,
			"pocetUchazecuNa1VPM": 0.600619195,
			"podilNezamestnanychOsobPNO": 2.3622755164,
			"rok": "2021",
			"uchazeciOZamestnaniUoZ": 1164,
			"uchazeciOZamestnaniUoZZeny": 673,
			"volnaPracovnaMistaVPM": 1938,
			"vyrazeniUchazeci": 191,
			"celkemObyvatelstvo15_64": 44491
		},
		{
			"okres": "Okres/3306",
			"absolventiSkolAMladistvi": 36,
			"dosazitelniUchazeci15_64": 636,
			"mesic": "07",
			"noveHlasenaAUvolnenaVPM": 368,
			"noveHlaseniUchazeci": 101,
			"obsazenaAZrusenaVPM": 373,
			"osobySeZdravotnimPostizenim": 166,
			"pocetOsobPobirajicichPodporu": 288,
			"pocetUchazecuNa1VPM": 0.3745210728,
			"podilNezamestnanychOsobPNO": 1.958670814,
			"rok": "2021",
			"uchazeciOZamestnaniUoZ": 782,
			"uchazeciOZamestnaniUoZZeny": 445,
			"volnaPracovnaMistaVPM": 2088,
			"vyrazeniUchazeci": 141,
			"celkemObyvatelstvo15_64": 32471
		},
		{
			"okres": "Okres/3307",
			"absolventiSkolAMladistvi": 49,
			"dosazitelniUchazeci15_64": 1093,
			"mesic": "07",
			"noveHlasenaAUvolnenaVPM": 510,
			"noveHlaseniUchazeci": 177,
			"obsazenaAZrusenaVPM": 504,
			"osobySeZdravotnimPostizenim": 362,
			"pocetOsobPobirajicichPodporu": 478,
			"pocetUchazecuNa1VPM": 0.9207988981,
			"podilNezamestnanychOsobPNO": 2.4715086831,
			"rok": "2021",
			"uchazeciOZamestnaniUoZ": 1337,
			"uchazeciOZamestnaniUoZZeny": 814,
			"volnaPracovnaMistaVPM": 1452,
			"vyrazeniUchazeci": 178,
			"celkemObyvatelstvo15_64": 44224
		},
		{
			"okres": "Okres/3308",
			"absolventiSkolAMladistvi": 122,
			"dosazitelniUchazeci15_64": 2268,
			"mesic": "07",
			"noveHlasenaAUvolnenaVPM": 456,
			"noveHlaseniUchazeci": 268,
			"obsazenaAZrusenaVPM": 347,
			"osobySeZdravotnimPostizenim": 383,
			"pocetOsobPobirajicichPodporu": 753,
			"pocetUchazecuNa1VPM": 0.6361502347,
			"podilNezamestnanychOsobPNO": 3.5453564897,
			"rok": "2021",
			"uchazeciOZamestnaniUoZ": 2439,
			"uchazeciOZamestnaniUoZZeny": 1361,
			"volnaPracovnaMistaVPM": 3834,
			"vyrazeniUchazeci": 271,
			"celkemObyvatelstvo15_64": 63971
		},
		{
			"okres": "Okres/3401",
			"absolventiSkolAMladistvi": 66,
			"dosazitelniUchazeci15_64": 1295,
			"mesic": "07",
			"noveHlasenaAUvolnenaVPM": 553,
			"noveHlaseniUchazeci": 141,
			"obsazenaAZrusenaVPM": 1279,
			"osobySeZdravotnimPostizenim": 254,
			"pocetOsobPobirajicichPodporu": 348,
			"pocetUchazecuNa1VPM": 0.5849379546,
			"podilNezamestnanychOsobPNO": 3.2946623925,
			"rok": "2021",
			"uchazeciOZamestnaniUoZ": 1367,
			"uchazeciOZamestnaniUoZZeny": 750,
			"volnaPracovnaMistaVPM": 2337,
			"vyrazeniUchazeci": 169,
			"celkemObyvatelstvo15_64": 39306
		},
		{
			"okres": "Okres/3404",
			"absolventiSkolAMladistvi": 56,
			"dosazitelniUchazeci15_64": 1278,
			"mesic": "07",
			"noveHlasenaAUvolnenaVPM": 631,
			"noveHlaseniUchazeci": 226,
			"obsazenaAZrusenaVPM": 406,
			"osobySeZdravotnimPostizenim": 274,
			"pocetOsobPobirajicichPodporu": 528,
			"pocetUchazecuNa1VPM": 0.4393010423,
			"podilNezamestnanychOsobPNO": 2.3643898468,
			"rok": "2021",
			"uchazeciOZamestnaniUoZ": 1433,
			"uchazeciOZamestnaniUoZZeny": 818,
			"volnaPracovnaMistaVPM": 3262,
			"vyrazeniUchazeci": 267,
			"celkemObyvatelstvo15_64": 54052
		},
		{
			"okres": "Okres/3405",
			"absolventiSkolAMladistvi": 116,
			"dosazitelniUchazeci15_64": 3622,
			"mesic": "07",
			"noveHlasenaAUvolnenaVPM": 1686,
			"noveHlaseniUchazeci": 634,
			"obsazenaAZrusenaVPM": 1461,
			"osobySeZdravotnimPostizenim": 562,
			"pocetOsobPobirajicichPodporu": 1378,
			"pocetUchazecuNa1VPM": 0.4249279693,
			"podilNezamestnanychOsobPNO": 2.9236320195,
			"rok": "2021",
			"uchazeciOZamestnaniUoZ": 3982,
			"uchazeciOZamestnaniUoZZeny": 2205,
			"volnaPracovnaMistaVPM": 9371,
			"vyrazeniUchazeci": 656,
			"celkemObyvatelstvo15_64": 123887
		},
		{
			"okres": "Okres/3406",
			"absolventiSkolAMladistvi": 27,
			"dosazitelniUchazeci15_64": 934,
			"mesic": "07",
			"noveHlasenaAUvolnenaVPM": 567,
			"noveHlaseniUchazeci": 129,
			"obsazenaAZrusenaVPM": 713,
			"osobySeZdravotnimPostizenim": 228,
			"pocetOsobPobirajicichPodporu": 373,
			"pocetUchazecuNa1VPM": 0.2346281909,
			"podilNezamestnanychOsobPNO": 2.3173878523,
			"rok": "2021",
			"uchazeciOZamestnaniUoZ": 1057,
			"uchazeciOZamestnaniUoZZeny": 583,
			"volnaPracovnaMistaVPM": 4505,
			"vyrazeniUchazeci": 150,
			"celkemObyvatelstvo15_64": 40304
		},
		{
			"okres": "Okres/3407",
			"absolventiSkolAMladistvi": 50,
			"dosazitelniUchazeci15_64": 1512,
			"mesic": "07",
			"noveHlasenaAUvolnenaVPM": 432,
			"noveHlaseniUchazeci": 194,
			"obsazenaAZrusenaVPM": 536,
			"osobySeZdravotnimPostizenim": 231,
			"pocetOsobPobirajicichPodporu": 562,
			"pocetUchazecuNa1VPM": 0.666275889,
			"podilNezamestnanychOsobPNO": 2.9123408517,
			"rok": "2021",
			"uchazeciOZamestnaniUoZ": 1705,
			"uchazeciOZamestnaniUoZZeny": 912,
			"volnaPracovnaMistaVPM": 2559,
			"vyrazeniUchazeci": 235,
			"celkemObyvatelstvo15_64": 51917
		},
		{
			"okres": "Okres/3408",
			"absolventiSkolAMladistvi": 23,
			"dosazitelniUchazeci15_64": 1015,
			"mesic": "07",
			"noveHlasenaAUvolnenaVPM": 442,
			"noveHlaseniUchazeci": 115,
			"obsazenaAZrusenaVPM": 446,
			"osobySeZdravotnimPostizenim": 255,
			"pocetOsobPobirajicichPodporu": 345,
			"pocetUchazecuNa1VPM": 0.6391509434,
			"podilNezamestnanychOsobPNO": 3.2316607234,
			"rok": "2021",
			"uchazeciOZamestnaniUoZ": 1084,
			"uchazeciOZamestnaniUoZZeny": 626,
			"volnaPracovnaMistaVPM": 1696,
			"vyrazeniUchazeci": 130,
			"celkemObyvatelstvo15_64": 31408
		},
		{
			"okres": "Okres/3410",
			"absolventiSkolAMladistvi": 36,
			"dosazitelniUchazeci15_64": 1200,
			"mesic": "07",
			"noveHlasenaAUvolnenaVPM": 3494,
			"noveHlaseniUchazeci": 169,
			"obsazenaAZrusenaVPM": 3621,
			"osobySeZdravotnimPostizenim": 258,
			"pocetOsobPobirajicichPodporu": 389,
			"pocetUchazecuNa1VPM": 0.1482938115,
			"podilNezamestnanychOsobPNO": 3.3313900225,
			"rok": "2021",
			"uchazeciOZamestnaniUoZ": 1282,
			"uchazeciOZamestnaniUoZZeny": 639,
			"volnaPracovnaMistaVPM": 8645,
			"vyrazeniUchazeci": 149,
			"celkemObyvatelstvo15_64": 36021
		},
		{
			"okres": "Okres/3402",
			"absolventiSkolAMladistvi": 70,
			"dosazitelniUchazeci15_64": 2218,
			"mesic": "07",
			"noveHlasenaAUvolnenaVPM": 962,
			"noveHlaseniUchazeci": 264,
			"obsazenaAZrusenaVPM": 367,
			"osobySeZdravotnimPostizenim": 226,
			"pocetOsobPobirajicichPodporu": 560,
			"pocetUchazecuNa1VPM": 0.8395549174,
			"podilNezamestnanychOsobPNO": 3.7897686498,
			"rok": "2021",
			"uchazeciOZamestnaniUoZ": 2339,
			"uchazeciOZamestnaniUoZZeny": 1227,
			"volnaPracovnaMistaVPM": 2786,
			"vyrazeniUchazeci": 344,
			"celkemObyvatelstvo15_64": 58526
		},
		{
			"okres": "Okres/3403",
			"absolventiSkolAMladistvi": 118,
			"dosazitelniUchazeci15_64": 3865,
			"mesic": "07",
			"noveHlasenaAUvolnenaVPM": 336,
			"noveHlaseniUchazeci": 338,
			"obsazenaAZrusenaVPM": 272,
			"osobySeZdravotnimPostizenim": 329,
			"pocetOsobPobirajicichPodporu": 976,
			"pocetUchazecuNa1VPM": 1.8465011287,
			"podilNezamestnanychOsobPNO": 5.3242048131,
			"rok": "2021",
			"uchazeciOZamestnaniUoZ": 4090,
			"uchazeciOZamestnaniUoZZeny": 2157,
			"volnaPracovnaMistaVPM": 2215,
			"vyrazeniUchazeci": 568,
			"celkemObyvatelstvo15_64": 72593
		},
		{
			"okres": "Okres/3409",
			"absolventiSkolAMladistvi": 126,
			"dosazitelniUchazeci15_64": 3296,
			"mesic": "07",
			"noveHlasenaAUvolnenaVPM": 109,
			"noveHlaseniUchazeci": 321,
			"obsazenaAZrusenaVPM": 78,
			"osobySeZdravotnimPostizenim": 408,
			"pocetOsobPobirajicichPodporu": 877,
			"pocetUchazecuNa1VPM": 4.8169398907,
			"podilNezamestnanychOsobPNO": 5.8385885354,
			"rok": "2021",
			"uchazeciOZamestnaniUoZ": 3526,
			"uchazeciOZamestnaniUoZZeny": 1817,
			"volnaPracovnaMistaVPM": 732,
			"vyrazeniUchazeci": 479,
			"celkemObyvatelstvo15_64": 56452
		},
		{
			"okres": "Okres/3502",
			"absolventiSkolAMladistvi": 154,
			"dosazitelniUchazeci15_64": 4190,
			"mesic": "07",
			"noveHlasenaAUvolnenaVPM": 162,
			"noveHlaseniUchazeci": 425,
			"obsazenaAZrusenaVPM": 165,
			"osobySeZdravotnimPostizenim": 653,
			"pocetOsobPobirajicichPodporu": 1076,
			"pocetUchazecuNa1VPM": 2.9280104712,
			"podilNezamestnanychOsobPNO": 5.2299166209,
			"rok": "2021",
			"uchazeciOZamestnaniUoZ": 4474,
			"uchazeciOZamestnaniUoZZeny": 2392,
			"volnaPracovnaMistaVPM": 1528,
			"vyrazeniUchazeci": 540,
			"celkemObyvatelstvo15_64": 80116
		},
		{
			"okres": "Okres/3503",
			"absolventiSkolAMladistvi": 177,
			"dosazitelniUchazeci15_64": 5004,
			"mesic": "07",
			"noveHlasenaAUvolnenaVPM": 1024,
			"noveHlaseniUchazeci": 468,
			"obsazenaAZrusenaVPM": 1807,
			"osobySeZdravotnimPostizenim": 748,
			"pocetOsobPobirajicichPodporu": 1125,
			"pocetUchazecuNa1VPM": 0.9554626432,
			"podilNezamestnanychOsobPNO": 6.1256717551,
			"rok": "2021",
			"uchazeciOZamestnaniUoZ": 5256,
			"uchazeciOZamestnaniUoZZeny": 2884,
			"volnaPracovnaMistaVPM": 5501,
			"vyrazeniUchazeci": 623,
			"celkemObyvatelstvo15_64": 81689
		},
		{
			"okres": "Okres/3506",
			"absolventiSkolAMladistvi": 100,
			"dosazitelniUchazeci15_64": 2552,
			"mesic": "07",
			"noveHlasenaAUvolnenaVPM": 326,
			"noveHlaseniUchazeci": 415,
			"obsazenaAZrusenaVPM": 260,
			"osobySeZdravotnimPostizenim": 588,
			"pocetOsobPobirajicichPodporu": 858,
			"pocetUchazecuNa1VPM": 1.8127463863,
			"podilNezamestnanychOsobPNO": 3.3975024629,
			"rok": "2021",
			"uchazeciOZamestnaniUoZ": 2759,
			"uchazeciOZamestnaniUoZZeny": 1620,
			"volnaPracovnaMistaVPM": 1522,
			"vyrazeniUchazeci": 499,
			"celkemObyvatelstvo15_64": 75114
		},
		{
			"okres": "Okres/3507",
			"absolventiSkolAMladistvi": 121,
			"dosazitelniUchazeci15_64": 3164,
			"mesic": "07",
			"noveHlasenaAUvolnenaVPM": 404,
			"noveHlaseniUchazeci": 389,
			"obsazenaAZrusenaVPM": 312,
			"osobySeZdravotnimPostizenim": 651,
			"pocetOsobPobirajicichPodporu": 942,
			"pocetUchazecuNa1VPM": 2.0469483568,
			"podilNezamestnanychOsobPNO": 5.7399949204,
			"rok": "2021",
			"uchazeciOZamestnaniUoZ": 3488,
			"uchazeciOZamestnaniUoZZeny": 1917,
			"volnaPracovnaMistaVPM": 1704,
			"vyrazeniUchazeci": 373,
			"celkemObyvatelstvo15_64": 55122
		},
		{
			"okres": "Okres/3508",
			"absolventiSkolAMladistvi": 205,
			"dosazitelniUchazeci15_64": 5105,
			"mesic": "07",
			"noveHlasenaAUvolnenaVPM": 110,
			"noveHlaseniUchazeci": 413,
			"obsazenaAZrusenaVPM": 127,
			"osobySeZdravotnimPostizenim": 739,
			"pocetOsobPobirajicichPodporu": 1148,
			"pocetUchazecuNa1VPM": 4.8459483526,
			"podilNezamestnanychOsobPNO": 7.1161727397,
			"rok": "2021",
			"uchazeciOZamestnaniUoZ": 5442,
			"uchazeciOZamestnaniUoZZeny": 2998,
			"volnaPracovnaMistaVPM": 1123,
			"vyrazeniUchazeci": 538,
			"celkemObyvatelstvo15_64": 71738
		},
		{
			"okres": "Okres/3509",
			"absolventiSkolAMladistvi": 167,
			"dosazitelniUchazeci15_64": 3834,
			"mesic": "07",
			"noveHlasenaAUvolnenaVPM": 305,
			"noveHlaseniUchazeci": 420,
			"obsazenaAZrusenaVPM": 252,
			"osobySeZdravotnimPostizenim": 758,
			"pocetOsobPobirajicichPodporu": 979,
			"pocetUchazecuNa1VPM": 1.5608365019,
			"podilNezamestnanychOsobPNO": 4.611110443,
			"rok": "2021",
			"uchazeciOZamestnaniUoZ": 4105,
			"uchazeciOZamestnaniUoZZeny": 2252,
			"volnaPracovnaMistaVPM": 2630,
			"vyrazeniUchazeci": 474,
			"celkemObyvatelstvo15_64": 83147
		},
		{
			"okres": "Okres/3510",
			"absolventiSkolAMladistvi": 171,
			"dosazitelniUchazeci15_64": 4709,
			"mesic": "07",
			"noveHlasenaAUvolnenaVPM": 181,
			"noveHlaseniUchazeci": 429,
			"obsazenaAZrusenaVPM": 174,
			"osobySeZdravotnimPostizenim": 572,
			"pocetOsobPobirajicichPodporu": 966,
			"pocetUchazecuNa1VPM": 4.826959847,
			"podilNezamestnanychOsobPNO": 6.2763235059,
			"rok": "2021",
			"uchazeciOZamestnaniUoZ": 5049,
			"uchazeciOZamestnaniUoZZeny": 2577,
			"volnaPracovnaMistaVPM": 1046,
			"vyrazeniUchazeci": 438,
			"celkemObyvatelstvo15_64": 75028
		},
		{
			"okres": "Okres/3501",
			"absolventiSkolAMladistvi": 94,
			"dosazitelniUchazeci15_64": 1919,
			"mesic": "07",
			"noveHlasenaAUvolnenaVPM": 381,
			"noveHlaseniUchazeci": 296,
			"obsazenaAZrusenaVPM": 303,
			"osobySeZdravotnimPostizenim": 444,
			"pocetOsobPobirajicichPodporu": 732,
			"pocetUchazecuNa1VPM": 1.3173652695,
			"podilNezamestnanychOsobPNO": 2.9075317041,
			"rok": "2021",
			"uchazeciOZamestnaniUoZ": 2200,
			"uchazeciOZamestnaniUoZZeny": 1256,
			"volnaPracovnaMistaVPM": 1670,
			"vyrazeniUchazeci": 350,
			"celkemObyvatelstvo15_64": 66001
		},
		{
			"okres": "Okres/3504",
			"absolventiSkolAMladistvi": 101,
			"dosazitelniUchazeci15_64": 2225,
			"mesic": "07",
			"noveHlasenaAUvolnenaVPM": 220,
			"noveHlaseniUchazeci": 251,
			"obsazenaAZrusenaVPM": 184,
			"osobySeZdravotnimPostizenim": 329,
			"pocetOsobPobirajicichPodporu": 706,
			"pocetUchazecuNa1VPM": 1.8400918133,
			"podilNezamestnanychOsobPNO": 3.9717248889,
			"rok": "2021",
			"uchazeciOZamestnaniUoZ": 2405,
			"uchazeciOZamestnaniUoZZeny": 1335,
			"volnaPracovnaMistaVPM": 1307,
			"vyrazeniUchazeci": 294,
			"celkemObyvatelstvo15_64": 56021
		},
		{
			"okres": "Okres/3505",
			"absolventiSkolAMladistvi": 217,
			"dosazitelniUchazeci15_64": 5147,
			"mesic": "07",
			"noveHlasenaAUvolnenaVPM": 1591,
			"noveHlaseniUchazeci": 611,
			"obsazenaAZrusenaVPM": 1524,
			"osobySeZdravotnimPostizenim": 687,
			"pocetOsobPobirajicichPodporu": 1480,
			"pocetUchazecuNa1VPM": 0.9419852448,
			"podilNezamestnanychOsobPNO": 4.6474879908,
			"rok": "2021",
			"uchazeciOZamestnaniUoZ": 5618,
			"uchazeciOZamestnaniUoZZeny": 2967,
			"volnaPracovnaMistaVPM": 5964,
			"vyrazeniUchazeci": 519,
			"celkemObyvatelstvo15_64": 110748
		},
		{
			"okres": "Okres/3608",
			"absolventiSkolAMladistvi": 82,
			"dosazitelniUchazeci15_64": 1737,
			"mesic": "07",
			"noveHlasenaAUvolnenaVPM": 240,
			"noveHlaseniUchazeci": 212,
			"obsazenaAZrusenaVPM": 145,
			"osobySeZdravotnimPostizenim": 307,
			"pocetOsobPobirajicichPodporu": 625,
			"pocetUchazecuNa1VPM": 1.1946614583,
			"podilNezamestnanychOsobPNO": 3.7890190433,
			"rok": "2021",
			"uchazeciOZamestnaniUoZ": 1835,
			"uchazeciOZamestnaniUoZZeny": 975,
			"volnaPracovnaMistaVPM": 1536,
			"vyrazeniUchazeci": 219,
			"celkemObyvatelstvo15_64": 45843
		},
		{
			"okres": "Okres/3602",
			"absolventiSkolAMladistvi": 165,
			"dosazitelniUchazeci15_64": 3023,
			"mesic": "07",
			"noveHlasenaAUvolnenaVPM": 653,
			"noveHlaseniUchazeci": 452,
			"obsazenaAZrusenaVPM": 585,
			"osobySeZdravotnimPostizenim": 577,
			"pocetOsobPobirajicichPodporu": 1050,
			"pocetUchazecuNa1VPM": 0.7020655122,
			"podilNezamestnanychOsobPNO": 2.9795580437,
			"rok": "2021",
			"uchazeciOZamestnaniUoZ": 3365,
			"uchazeciOZamestnaniUoZZeny": 1801,
			"volnaPracovnaMistaVPM": 4793,
			"vyrazeniUchazeci": 424,
			"celkemObyvatelstvo15_64": 101458
		},
		{
			"okres": "Okres/3604",
			"absolventiSkolAMladistvi": 63,
			"dosazitelniUchazeci15_64": 921,
			"mesic": "07",
			"noveHlasenaAUvolnenaVPM": 364,
			"noveHlaseniUchazeci": 171,
			"obsazenaAZrusenaVPM": 608,
			"osobySeZdravotnimPostizenim": 181,
			"pocetOsobPobirajicichPodporu": 429,
			"pocetUchazecuNa1VPM": 0.5810736027,
			"podilNezamestnanychOsobPNO": 1.8366370199,
			"rok": "2021",
			"uchazeciOZamestnaniUoZ": 1050,
			"uchazeciOZamestnaniUoZZeny": 615,
			"volnaPracovnaMistaVPM": 1807,
			"vyrazeniUchazeci": 211,
			"celkemObyvatelstvo15_64": 50146
		},
		{
			"okres": "Okres/3605",
			"absolventiSkolAMladistvi": 78,
			"dosazitelniUchazeci15_64": 2337,
			"mesic": "07",
			"noveHlasenaAUvolnenaVPM": 299,
			"noveHlaseniUchazeci": 369,
			"obsazenaAZrusenaVPM": 488,
			"osobySeZdravotnimPostizenim": 420,
			"pocetOsobPobirajicichPodporu": 819,
			"pocetUchazecuNa1VPM": 1.0273405137,
			"podilNezamestnanychOsobPNO": 3.4432968425,
			"rok": "2021",
			"uchazeciOZamestnaniUoZ": 2480,
			"uchazeciOZamestnaniUoZZeny": 1260,
			"volnaPracovnaMistaVPM": 2414,
			"vyrazeniUchazeci": 347,
			"celkemObyvatelstvo15_64": 67871
		},
		{
			"okres": "Okres/3607",
			"absolventiSkolAMladistvi": 20,
			"dosazitelniUchazeci15_64": 854,
			"mesic": "07",
			"noveHlasenaAUvolnenaVPM": 428,
			"noveHlaseniUchazeci": 170,
			"obsazenaAZrusenaVPM": 318,
			"osobySeZdravotnimPostizenim": 177,
			"pocetOsobPobirajicichPodporu": 423,
			"pocetUchazecuNa1VPM": 0.401039411,
			"podilNezamestnanychOsobPNO": 1.7130706892,
			"rok": "2021",
			"uchazeciOZamestnaniUoZ": 926,
			"uchazeciOZamestnaniUoZZeny": 553,
			"volnaPracovnaMistaVPM": 2309,
			"vyrazeniUchazeci": 167,
			"celkemObyvatelstvo15_64": 49852
		},
		{
			"okres": "Okres/3610",
			"absolventiSkolAMladistvi": 82,
			"dosazitelniUchazeci15_64": 2315,
			"mesic": "07",
			"noveHlasenaAUvolnenaVPM": 325,
			"noveHlaseniUchazeci": 313,
			"obsazenaAZrusenaVPM": 247,
			"osobySeZdravotnimPostizenim": 497,
			"pocetOsobPobirajicichPodporu": 861,
			"pocetUchazecuNa1VPM": 1.4581136497,
			"podilNezamestnanychOsobPNO": 3.1640379411,
			"rok": "2021",
			"uchazeciOZamestnaniUoZ": 2489,
			"uchazeciOZamestnaniUoZZeny": 1315,
			"volnaPracovnaMistaVPM": 1707,
			"vyrazeniUchazeci": 352,
			"celkemObyvatelstvo15_64": 73166
		},
		{
			"okres": "Okres/3603",
			"absolventiSkolAMladistvi": 94,
			"dosazitelniUchazeci15_64": 1662,
			"mesic": "07",
			"noveHlasenaAUvolnenaVPM": 661,
			"noveHlaseniUchazeci": 299,
			"obsazenaAZrusenaVPM": 271,
			"osobySeZdravotnimPostizenim": 356,
			"pocetOsobPobirajicichPodporu": 677,
			"pocetUchazecuNa1VPM": 0.5434914842,
			"podilNezamestnanychOsobPNO": 2.523189968,
			"rok": "2021",
			"uchazeciOZamestnaniUoZ": 1787,
			"uchazeciOZamestnaniUoZZeny": 1039,
			"volnaPracovnaMistaVPM": 3288,
			"vyrazeniUchazeci": 332,
			"celkemObyvatelstvo15_64": 65869
		},
		{
			"okres": "Okres/3606",
			"absolventiSkolAMladistvi": 119,
			"dosazitelniUchazeci15_64": 2597,
			"mesic": "07",
			"noveHlasenaAUvolnenaVPM": 1998,
			"noveHlaseniUchazeci": 442,
			"obsazenaAZrusenaVPM": 1719,
			"osobySeZdravotnimPostizenim": 431,
			"pocetOsobPobirajicichPodporu": 1040,
			"pocetUchazecuNa1VPM": 0.2857569424,
			"podilNezamestnanychOsobPNO": 2.3137918746,
			"rok": "2021",
			"uchazeciOZamestnaniUoZ": 2871,
			"uchazeciOZamestnaniUoZZeny": 1645,
			"volnaPracovnaMistaVPM": 10047,
			"vyrazeniUchazeci": 467,
			"celkemObyvatelstvo15_64": 112240
		},
		{
			"okres": "Okres/3609",
			"absolventiSkolAMladistvi": 68,
			"dosazitelniUchazeci15_64": 1485,
			"mesic": "07",
			"noveHlasenaAUvolnenaVPM": 508,
			"noveHlaseniUchazeci": 271,
			"obsazenaAZrusenaVPM": 319,
			"osobySeZdravotnimPostizenim": 396,
			"pocetOsobPobirajicichPodporu": 672,
			"pocetUchazecuNa1VPM": 0.4835892803,
			"podilNezamestnanychOsobPNO": 2.256976108,
			"rok": "2021",
			"uchazeciOZamestnaniUoZ": 1606,
			"uchazeciOZamestnaniUoZZeny": 860,
			"volnaPracovnaMistaVPM": 3321,
			"vyrazeniUchazeci": 264,
			"celkemObyvatelstvo15_64": 65796
		},
		{
			"okres": "Okres/3611",
			"absolventiSkolAMladistvi": 96,
			"dosazitelniUchazeci15_64": 2020,
			"mesic": "07",
			"noveHlasenaAUvolnenaVPM": 436,
			"noveHlaseniUchazeci": 339,
			"obsazenaAZrusenaVPM": 301,
			"osobySeZdravotnimPostizenim": 458,
			"pocetOsobPobirajicichPodporu": 861,
			"pocetUchazecuNa1VPM": 0.6098807496,
			"podilNezamestnanychOsobPNO": 2.3194130278,
			"rok": "2021",
			"uchazeciOZamestnaniUoZ": 2148,
			"uchazeciOZamestnaniUoZZeny": 1193,
			"volnaPracovnaMistaVPM": 3522,
			"vyrazeniUchazeci": 351,
			"celkemObyvatelstvo15_64": 87091
		},
		{
			"okres": "Okres/3601",
			"absolventiSkolAMladistvi": 79,
			"dosazitelniUchazeci15_64": 1591,
			"mesic": "07",
			"noveHlasenaAUvolnenaVPM": 254,
			"noveHlaseniUchazeci": 249,
			"obsazenaAZrusenaVPM": 174,
			"osobySeZdravotnimPostizenim": 454,
			"pocetOsobPobirajicichPodporu": 639,
			"pocetUchazecuNa1VPM": 1.0099241097,
			"podilNezamestnanychOsobPNO": 2.6893171062,
			"rok": "2021",
			"uchazeciOZamestnaniUoZ": 1730,
			"uchazeciOZamestnaniUoZZeny": 1038,
			"volnaPracovnaMistaVPM": 1713,
			"vyrazeniUchazeci": 205,
			"celkemObyvatelstvo15_64": 59160
		},
		{
			"okres": "Okres/3707",
			"absolventiSkolAMladistvi": 87,
			"dosazitelniUchazeci15_64": 1995,
			"mesic": "07",
			"noveHlasenaAUvolnenaVPM": 621,
			"noveHlaseniUchazeci": 385,
			"obsazenaAZrusenaVPM": 550,
			"osobySeZdravotnimPostizenim": 307,
			"pocetOsobPobirajicichPodporu": 827,
			"pocetUchazecuNa1VPM": 0.5765153574,
			"podilNezamestnanychOsobPNO": 2.7593360996,
			"rok": "2021",
			"uchazeciOZamestnaniUoZ": 2121,
			"uchazeciOZamestnaniUoZZeny": 1183,
			"volnaPracovnaMistaVPM": 3679,
			"vyrazeniUchazeci": 296,
			"celkemObyvatelstvo15_64": 72300
		},
		{
			"okres": "Okres/3304",
			"absolventiSkolAMladistvi": 33,
			"dosazitelniUchazeci15_64": 756,
			"mesic": "07",
			"noveHlasenaAUvolnenaVPM": 499,
			"noveHlaseniUchazeci": 183,
			"obsazenaAZrusenaVPM": 415,
			"osobySeZdravotnimPostizenim": 171,
			"pocetOsobPobirajicichPodporu": 427,
			"pocetUchazecuNa1VPM": 0.2528,
			"podilNezamestnanychOsobPNO": 1.6549187864,
			"rok": "2021",
			"uchazeciOZamestnaniUoZ": 790,
			"uchazeciOZamestnaniUoZZeny": 472,
			"volnaPracovnaMistaVPM": 3125,
			"vyrazeniUchazeci": 149,
			"celkemObyvatelstvo15_64": 45682
		},
		{
			"okres": "Okres/3710",
			"absolventiSkolAMladistvi": 120,
			"dosazitelniUchazeci15_64": 2477,
			"mesic": "07",
			"noveHlasenaAUvolnenaVPM": 109,
			"noveHlaseniUchazeci": 325,
			"obsazenaAZrusenaVPM": 102,
			"osobySeZdravotnimPostizenim": 304,
			"pocetOsobPobirajicichPodporu": 842,
			"pocetUchazecuNa1VPM": 1.7128270581,
			"podilNezamestnanychOsobPNO": 3.5263300258,
			"rok": "2021",
			"uchazeciOZamestnaniUoZ": 2684,
			"uchazeciOZamestnaniUoZZeny": 1476,
			"volnaPracovnaMistaVPM": 1567,
			"vyrazeniUchazeci": 272,
			"celkemObyvatelstvo15_64": 70243
		},
		{
			"okres": "Okres/3714",
			"absolventiSkolAMladistvi": 99,
			"dosazitelniUchazeci15_64": 2372,
			"mesic": "07",
			"noveHlasenaAUvolnenaVPM": 295,
			"noveHlaseniUchazeci": 364,
			"obsazenaAZrusenaVPM": 239,
			"osobySeZdravotnimPostizenim": 565,
			"pocetOsobPobirajicichPodporu": 939,
			"pocetUchazecuNa1VPM": 1.720293725,
			"podilNezamestnanychOsobPNO": 3.1639322396,
			"rok": "2021",
			"uchazeciOZamestnaniUoZ": 2577,
			"uchazeciOZamestnaniUoZZeny": 1369,
			"volnaPracovnaMistaVPM": 1498,
			"vyrazeniUchazeci": 291,
			"celkemObyvatelstvo15_64": 74970
		},
		{
			"okres": "Okres/3701",
			"absolventiSkolAMladistvi": 84,
			"dosazitelniUchazeci15_64": 2091,
			"mesic": "07",
			"noveHlasenaAUvolnenaVPM": 325,
			"noveHlaseniUchazeci": 311,
			"obsazenaAZrusenaVPM": 291,
			"osobySeZdravotnimPostizenim": 553,
			"pocetOsobPobirajicichPodporu": 715,
			"pocetUchazecuNa1VPM": 1.9313232831,
			"podilNezamestnanychOsobPNO": 3.0721537399,
			"rok": "2021",
			"uchazeciOZamestnaniUoZ": 2306,
			"uchazeciOZamestnaniUoZZeny": 1200,
			"volnaPracovnaMistaVPM": 1194,
			"vyrazeniUchazeci": 248,
			"celkemObyvatelstvo15_64": 68063
		},
		{
			"okres": "Okres/3702",
			"absolventiSkolAMladistvi": 496,
			"dosazitelniUchazeci15_64": 12101,
			"mesic": "07",
			"noveHlasenaAUvolnenaVPM": 2130,
			"noveHlaseniUchazeci": 1276,
			"obsazenaAZrusenaVPM": 1423,
			"osobySeZdravotnimPostizenim": 1328,
			"pocetOsobPobirajicichPodporu": 2961,
			"pocetUchazecuNa1VPM": 0.7557680197,
			"podilNezamestnanychOsobPNO": 4.9830548955,
			"rok": "2021",
			"uchazeciOZamestnaniUoZ": 13201,
			"uchazeciOZamestnaniUoZZeny": 6942,
			"volnaPracovnaMistaVPM": 17467,
			"vyrazeniUchazeci": 1187,
			"celkemObyvatelstvo15_64": 242843
		},
		{
			"okres": "Okres/3703",
			"absolventiSkolAMladistvi": 202,
			"dosazitelniUchazeci15_64": 4370,
			"mesic": "07",
			"noveHlasenaAUvolnenaVPM": 1712,
			"noveHlaseniUchazeci": 591,
			"obsazenaAZrusenaVPM": 1308,
			"osobySeZdravotnimPostizenim": 816,
			"pocetOsobPobirajicichPodporu": 1610,
			"pocetUchazecuNa1VPM": 0.8491285403,
			"podilNezamestnanychOsobPNO": 3.055623536,
			"rok": "2021",
			"uchazeciOZamestnaniUoZ": 4677,
			"uchazeciOZamestnaniUoZZeny": 2510,
			"volnaPracovnaMistaVPM": 5508,
			"vyrazeniUchazeci": 497,
			"celkemObyvatelstvo15_64": 143015
		},
		{
			"okres": "Okres/3704",
			"absolventiSkolAMladistvi": 106,
			"dosazitelniUchazeci15_64": 2289,
			"mesic": "07",
			"noveHlasenaAUvolnenaVPM": 585,
			"noveHlaseniUchazeci": 371,
			"obsazenaAZrusenaVPM": 446,
			"osobySeZdravotnimPostizenim": 458,
			"pocetOsobPobirajicichPodporu": 910,
			"pocetUchazecuNa1VPM": 1.0716798593,
			"podilNezamestnanychOsobPNO": 3.0682000965,
			"rok": "2021",
			"uchazeciOZamestnaniUoZ": 2437,
			"uchazeciOZamestnaniUoZZeny": 1305,
			"volnaPracovnaMistaVPM": 2274,
			"vyrazeniUchazeci": 364,
			"celkemObyvatelstvo15_64": 74604
		},
		{
			"okres": "Okres/3706",
			"absolventiSkolAMladistvi": 206,
			"dosazitelniUchazeci15_64": 4826,
			"mesic": "07",
			"noveHlasenaAUvolnenaVPM": 710,
			"noveHlaseniUchazeci": 540,
			"obsazenaAZrusenaVPM": 760,
			"osobySeZdravotnimPostizenim": 1033,
			"pocetOsobPobirajicichPodporu": 1416,
			"pocetUchazecuNa1VPM": 2.5216138329,
			"podilNezamestnanychOsobPNO": 4.9033752616,
			"rok": "2021",
			"uchazeciOZamestnaniUoZ": 5250,
			"uchazeciOZamestnaniUoZZeny": 2610,
			"volnaPracovnaMistaVPM": 2082,
			"vyrazeniUchazeci": 566,
			"celkemObyvatelstvo15_64": 98422
		},
		{
			"okres": "Okres/3712",
			"absolventiSkolAMladistvi": 67,
			"dosazitelniUchazeci15_64": 1445,
			"mesic": "07",
			"noveHlasenaAUvolnenaVPM": 141,
			"noveHlaseniUchazeci": 219,
			"obsazenaAZrusenaVPM": 136,
			"osobySeZdravotnimPostizenim": 373,
			"pocetOsobPobirajicichPodporu": 540,
			"pocetUchazecuNa1VPM": 0.8358050847,
			"podilNezamestnanychOsobPNO": 2.4586956152,
			"rok": "2021",
			"uchazeciOZamestnaniUoZ": 1578,
			"uchazeciOZamestnaniUoZZeny": 878,
			"volnaPracovnaMistaVPM": 1888,
			"vyrazeniUchazeci": 192,
			"celkemObyvatelstvo15_64": 58771
		},
		{
			"okres": "Okres/3713",
			"absolventiSkolAMladistvi": 128,
			"dosazitelniUchazeci15_64": 3405,
			"mesic": "07",
			"noveHlasenaAUvolnenaVPM": 309,
			"noveHlaseniUchazeci": 423,
			"obsazenaAZrusenaVPM": 309,
			"osobySeZdravotnimPostizenim": 487,
			"pocetOsobPobirajicichPodporu": 1067,
			"pocetUchazecuNa1VPM": 2.5870827286,
			"podilNezamestnanychOsobPNO": 4.6752711795,
			"rok": "2021",
			"uchazeciOZamestnaniUoZ": 3565,
			"uchazeciOZamestnaniUoZZeny": 2003,
			"volnaPracovnaMistaVPM": 1378,
			"vyrazeniUchazeci": 473,
			"celkemObyvatelstvo15_64": 72830
		},
		{
			"okres": "Okres/3811",
			"absolventiSkolAMladistvi": 30,
			"dosazitelniUchazeci15_64": 897,
			"mesic": "07",
			"noveHlasenaAUvolnenaVPM": 80,
			"noveHlaseniUchazeci": 145,
			"obsazenaAZrusenaVPM": 68,
			"osobySeZdravotnimPostizenim": 150,
			"pocetOsobPobirajicichPodporu": 324,
			"pocetUchazecuNa1VPM": 2.1932059448,
			"podilNezamestnanychOsobPNO": 3.7851295468,
			"rok": "2021",
			"uchazeciOZamestnaniUoZ": 1033,
			"uchazeciOZamestnaniUoZZeny": 512,
			"volnaPracovnaMistaVPM": 471,
			"vyrazeniUchazeci": 226,
			"celkemObyvatelstvo15_64": 23698
		},
		{
			"okres": "Okres/3805",
			"absolventiSkolAMladistvi": 243,
			"dosazitelniUchazeci15_64": 4816,
			"mesic": "07",
			"noveHlasenaAUvolnenaVPM": 706,
			"noveHlaseniUchazeci": 687,
			"obsazenaAZrusenaVPM": 683,
			"osobySeZdravotnimPostizenim": 808,
			"pocetOsobPobirajicichPodporu": 1725,
			"pocetUchazecuNa1VPM": 1.3633190118,
			"podilNezamestnanychOsobPNO": 3.2465081163,
			"rok": "2021",
			"uchazeciOZamestnaniUoZ": 5077,
			"uchazeciOZamestnaniUoZZeny": 2614,
			"volnaPracovnaMistaVPM": 3724,
			"vyrazeniUchazeci": 787,
			"celkemObyvatelstvo15_64": 148344
		},
		{
			"okres": "Okres/3709",
			"absolventiSkolAMladistvi": 55,
			"dosazitelniUchazeci15_64": 1578,
			"mesic": "07",
			"noveHlasenaAUvolnenaVPM": 147,
			"noveHlaseniUchazeci": 252,
			"obsazenaAZrusenaVPM": 77,
			"osobySeZdravotnimPostizenim": 333,
			"pocetOsobPobirajicichPodporu": 509,
			"pocetUchazecuNa1VPM": 0.9178590355,
			"podilNezamestnanychOsobPNO": 2.3114782914,
			"rok": "2021",
			"uchazeciOZamestnaniUoZ": 1732,
			"uchazeciOZamestnaniUoZZeny": 1013,
			"volnaPracovnaMistaVPM": 1887,
			"vyrazeniUchazeci": 294,
			"celkemObyvatelstvo15_64": 68268
		},
		{
			"okres": "Okres/3808",
			"absolventiSkolAMladistvi": 155,
			"dosazitelniUchazeci15_64": 3648,
			"mesic": "07",
			"noveHlasenaAUvolnenaVPM": 314,
			"noveHlaseniUchazeci": 375,
			"obsazenaAZrusenaVPM": 396,
			"osobySeZdravotnimPostizenim": 577,
			"pocetOsobPobirajicichPodporu": 994,
			"pocetUchazecuNa1VPM": 2.4601148692,
			"podilNezamestnanychOsobPNO": 4.4630404463,
			"rok": "2021",
			"uchazeciOZamestnaniUoZ": 3855,
			"uchazeciOZamestnaniUoZZeny": 2103,
			"volnaPracovnaMistaVPM": 1567,
			"vyrazeniUchazeci": 468,
			"celkemObyvatelstvo15_64": 81738
		},
		{
			"okres": "Okres/3809",
			"absolventiSkolAMladistvi": 105,
			"dosazitelniUchazeci15_64": 2727,
			"mesic": "07",
			"noveHlasenaAUvolnenaVPM": 304,
			"noveHlaseniUchazeci": 384,
			"obsazenaAZrusenaVPM": 193,
			"osobySeZdravotnimPostizenim": 552,
			"pocetOsobPobirajicichPodporu": 948,
			"pocetUchazecuNa1VPM": 1.8996088657,
			"podilNezamestnanychOsobPNO": 3.6397853768,
			"rok": "2021",
			"uchazeciOZamestnaniUoZ": 2914,
			"uchazeciOZamestnaniUoZZeny": 1540,
			"volnaPracovnaMistaVPM": 1534,
			"vyrazeniUchazeci": 450,
			"celkemObyvatelstvo15_64": 74922
		},
		{
			"okres": "Okres/3708",
			"absolventiSkolAMladistvi": 67,
			"dosazitelniUchazeci15_64": 1829,
			"mesic": "07",
			"noveHlasenaAUvolnenaVPM": 201,
			"noveHlaseniUchazeci": 290,
			"obsazenaAZrusenaVPM": 164,
			"osobySeZdravotnimPostizenim": 381,
			"pocetOsobPobirajicichPodporu": 696,
			"pocetUchazecuNa1VPM": 1.4391304348,
			"podilNezamestnanychOsobPNO": 2.7723042411,
			"rok": "2021",
			"uchazeciOZamestnaniUoZ": 1986,
			"uchazeciOZamestnaniUoZZeny": 1033,
			"volnaPracovnaMistaVPM": 1380,
			"vyrazeniUchazeci": 301,
			"celkemObyvatelstvo15_64": 65974
		},
		{
			"okres": "Okres/3711",
			"absolventiSkolAMladistvi": 105,
			"dosazitelniUchazeci15_64": 2295,
			"mesic": "07",
			"noveHlasenaAUvolnenaVPM": 429,
			"noveHlaseniUchazeci": 375,
			"obsazenaAZrusenaVPM": 440,
			"osobySeZdravotnimPostizenim": 566,
			"pocetOsobPobirajicichPodporu": 920,
			"pocetUchazecuNa1VPM": 0.8741473397,
			"podilNezamestnanychOsobPNO": 2.5468023482,
			"rok": "2021",
			"uchazeciOZamestnaniUoZ": 2563,
			"uchazeciOZamestnaniUoZZeny": 1467,
			"volnaPracovnaMistaVPM": 2932,
			"vyrazeniUchazeci": 332,
			"celkemObyvatelstvo15_64": 90113
		},
		{
			"okres": "Okres/3810",
			"absolventiSkolAMladistvi": 129,
			"dosazitelniUchazeci15_64": 3380,
			"mesic": "07",
			"noveHlasenaAUvolnenaVPM": 515,
			"noveHlaseniUchazeci": 440,
			"obsazenaAZrusenaVPM": 347,
			"osobySeZdravotnimPostizenim": 485,
			"pocetOsobPobirajicichPodporu": 1252,
			"pocetUchazecuNa1VPM": 1.0516743649,
			"podilNezamestnanychOsobPNO": 3.7284620646,
			"rok": "2021",
			"uchazeciOZamestnaniUoZ": 3643,
			"uchazeciOZamestnaniUoZZeny": 1776,
			"volnaPracovnaMistaVPM": 3464,
			"vyrazeniUchazeci": 490,
			"celkemObyvatelstvo15_64": 90654
		},
		{
			"okres": "Okres/3705",
			"absolventiSkolAMladistvi": 131,
			"dosazitelniUchazeci15_64": 3197,
			"mesic": "07",
			"noveHlasenaAUvolnenaVPM": 1083,
			"noveHlaseniUchazeci": 525,
			"obsazenaAZrusenaVPM": 762,
			"osobySeZdravotnimPostizenim": 624,
			"pocetOsobPobirajicichPodporu": 1371,
			"pocetUchazecuNa1VPM": 0.649478673,
			"podilNezamestnanychOsobPNO": 2.651087966,
			"rok": "2021",
			"uchazeciOZamestnaniUoZ": 3426,
			"uchazeciOZamestnaniUoZZeny": 1826,
			"volnaPracovnaMistaVPM": 5275,
			"vyrazeniUchazeci": 511,
			"celkemObyvatelstvo15_64": 120592
		},
		{
			"okres": "Okres/3801",
			"absolventiSkolAMladistvi": 89,
			"dosazitelniUchazeci15_64": 3289,
			"mesic": "07",
			"noveHlasenaAUvolnenaVPM": 203,
			"noveHlaseniUchazeci": 338,
			"obsazenaAZrusenaVPM": 168,
			"osobySeZdravotnimPostizenim": 670,
			"pocetOsobPobirajicichPodporu": 814,
			"pocetUchazecuNa1VPM": 3.7569892473,
			"podilNezamestnanychOsobPNO": 5.7101685793,
			"rok": "2021",
			"uchazeciOZamestnaniUoZ": 3494,
			"uchazeciOZamestnaniUoZZeny": 1867,
			"volnaPracovnaMistaVPM": 930,
			"vyrazeniUchazeci": 339,
			"celkemObyvatelstvo15_64": 57599
		},
		{
			"okres": "Okres/3802",
			"absolventiSkolAMladistvi": 146,
			"dosazitelniUchazeci15_64": 4319,
			"mesic": "07",
			"noveHlasenaAUvolnenaVPM": 338,
			"noveHlaseniUchazeci": 663,
			"obsazenaAZrusenaVPM": 356,
			"osobySeZdravotnimPostizenim": 925,
			"pocetOsobPobirajicichPodporu": 1724,
			"pocetUchazecuNa1VPM": 2.1602387511,
			"podilNezamestnanychOsobPNO": 3.1479362395,
			"rok": "2021",
			"uchazeciOZamestnaniUoZ": 4705,
			"uchazeciOZamestnaniUoZZeny": 2338,
			"volnaPracovnaMistaVPM": 2178,
			"vyrazeniUchazeci": 600,
			"celkemObyvatelstvo15_64": 137201
		},
		{
			"okres": "Okres/3803",
			"absolventiSkolAMladistvi": 339,
			"dosazitelniUchazeci15_64": 14032,
			"mesic": "07",
			"noveHlasenaAUvolnenaVPM": 182,
			"noveHlaseniUchazeci": 1044,
			"obsazenaAZrusenaVPM": 214,
			"osobySeZdravotnimPostizenim": 2001,
			"pocetOsobPobirajicichPodporu": 3323,
			"pocetUchazecuNa1VPM": 10.4026893135,
			"podilNezamestnanychOsobPNO": 9.0093676364,
			"rok": "2021",
			"uchazeciOZamestnaniUoZ": 14699,
			"uchazeciOZamestnaniUoZZeny": 6610,
			"volnaPracovnaMistaVPM": 1413,
			"vyrazeniUchazeci": 1041,
			"celkemObyvatelstvo15_64": 155749
		},
		{
			"okres": "Okres/3804",
			"absolventiSkolAMladistvi": 110,
			"dosazitelniUchazeci15_64": 3148,
			"mesic": "07",
			"noveHlasenaAUvolnenaVPM": 498,
			"noveHlaseniUchazeci": 471,
			"obsazenaAZrusenaVPM": 572,
			"osobySeZdravotnimPostizenim": 531,
			"pocetOsobPobirajicichPodporu": 1144,
			"pocetUchazecuNa1VPM": 1.3393792825,
			"podilNezamestnanychOsobPNO": 3.2596427647,
			"rok": "2021",
			"uchazeciOZamestnaniUoZ": 3323,
			"uchazeciOZamestnaniUoZZeny": 1698,
			"volnaPracovnaMistaVPM": 2481,
			"vyrazeniUchazeci": 419,
			"celkemObyvatelstvo15_64": 96575
		},
		{
			"okres": "Okres/3806",
			"absolventiSkolAMladistvi": 141,
			"dosazitelniUchazeci15_64": 3146,
			"mesic": "07",
			"noveHlasenaAUvolnenaVPM": 427,
			"noveHlaseniUchazeci": 452,
			"obsazenaAZrusenaVPM": 306,
			"osobySeZdravotnimPostizenim": 621,
			"pocetOsobPobirajicichPodporu": 1076,
			"pocetUchazecuNa1VPM": 1.9396162528,
			"podilNezamestnanychOsobPNO": 2.8057971014,
			"rok": "2021",
			"uchazeciOZamestnaniUoZ": 3437,
			"uchazeciOZamestnaniUoZZeny": 1665,
			"volnaPracovnaMistaVPM": 1772,
			"vyrazeniUchazeci": 412,
			"celkemObyvatelstvo15_64": 112125
		},
		{
			"okres": "Okres/3807",
			"absolventiSkolAMladistvi": 535,
			"dosazitelniUchazeci15_64": 13693,
			"mesic": "07",
			"noveHlasenaAUvolnenaVPM": 723,
			"noveHlaseniUchazeci": 1270,
			"obsazenaAZrusenaVPM": 1036,
			"osobySeZdravotnimPostizenim": 2258,
			"pocetOsobPobirajicichPodporu": 2932,
			"pocetUchazecuNa1VPM": 2.9016815035,
			"podilNezamestnanychOsobPNO": 6.7294413674,
			"rok": "2021",
			"uchazeciOZamestnaniUoZ": 14668,
			"uchazeciOZamestnaniUoZZeny": 7668,
			"volnaPracovnaMistaVPM": 5055,
			"vyrazeniUchazeci": 1198,
			"celkemObyvatelstvo15_64": 203479
		}
	]
}